chartlets/__init__.py
chartlets/callback.py
chartlets/channel.py
chartlets/component.py
chartlets/container.py
chartlets/contribution.py
chartlets/extension.py
chartlets/extensioncontext.py
chartlets/response.py
chartlets/version.py
chartlets/components/__init__.py
chartlets/components/box.py
chartlets/components/button.py
chartlets/components/checkbox.py
chartlets/components/datagrid.py
chartlets/components/dialog.py
chartlets/components/divider.py
chartlets/components/progress.py
chartlets/components/radiogroup.py
chartlets/components/select.py
chartlets/components/slider.py
chartlets/components/switch.py
chartlets/components/table.py
chartlets/components/tabs.py
chartlets/components/typography.py
chartlets/components/charts/__init__.py
chartlets/components/charts/vega.py
chartlets/controllers/__init__.py
chartlets/controllers/_helpers.py
chartlets/controllers/callback.py
chartlets/controllers/contributions.py
chartlets/controllers/layout.py
chartlets/util/__init__.py
chartlets/util/assertions.py
chartlets/util/logger.py
chartlets-0.1.7.dist-info/licenses/LICENSE
demo/my_extension/__init__.py
demo/my_extension/my_panel_1.py
demo/my_extension/my_panel_2.py
demo/my_extension/my_panel_3.py
demo/my_extension/my_panel_4.py
demo/my_extension/my_panel_5.py
demo/my_extension/my_panel_6.py
demo/my_extension/my_panel_7.py
demo/my_extension/my_panel_8.py
demo/server/__init__.py
demo/server/app.py
demo/server/context.py
demo/server/main.py
demo/server/panel.py
tests/components/__init__.py
tests/components/box_test.py
tests/components/button_test.py
tests/components/checkbox_test.py
tests/components/datagrid_test.py
tests/components/divider_test.py
tests/components/progress_test.py
tests/components/radiogroup_test.py
tests/components/select_test.py
tests/components/slider_test.py
tests/components/switch_test.py
tests/components/table_test.py
tests/components/tabs_test.py
tests/components/typography_test.py
tests/components/charts/__init__.py
tests/components/charts/vega_no_altair_test.py
chartlets-0.1.7.dist-info/METADATA
chartlets-0.1.7.dist-info/WHEEL
chartlets-0.1.7.dist-info/top_level.txt
chartlets-0.1.7.dist-info/RECORD
