Metadata-Version: 2.4
Name: chartlets
Version: 0.1.7
Summary: Backend for server-configured UI contributions.
Author: chartlets Development Team
License: MIT
Project-URL: Documentation, https://bcdev.github.io/chartlets
Project-URL: Repository, https://github.com/bcdev/chartlets
Project-URL: Changelog, https://github.com/bcdev/chartlets/blob/main/chartlets.py/CHANGES.md
Keywords: dashboard,charts,vega,altair,plots
Classifier: Development Status :: 5 - Production/Stable
Classifier: Intended Audience :: Science/Research
Classifier: Intended Audience :: Developers
Classifier: License :: OSI Approved :: MIT License
Classifier: Programming Language :: Python :: 3
Classifier: Programming Language :: Python :: 3.10
Classifier: Programming Language :: Python :: 3.11
Classifier: Programming Language :: Python :: 3.12
Classifier: Programming Language :: Python :: 3.13
Classifier: Topic :: Software Development
Classifier: Topic :: Scientific/Engineering
Classifier: Typing :: Typed
Classifier: Operating System :: Microsoft :: Windows
Classifier: Operating System :: POSIX
Classifier: Operating System :: Unix
Classifier: Operating System :: MacOS
Requires-Python: <3.14,>=3.10
License-File: LICENSE
Provides-Extra: opt
Requires-Dist: altair<6.0.0,>=5.5.0; extra == "opt"
Provides-Extra: dev
Requires-Dist: altair<6.0.0,>=5.5.0; extra == "dev"
Requires-Dist: black; extra == "dev"
Requires-Dist: flake8; extra == "dev"
Requires-Dist: pytest; extra == "dev"
Requires-Dist: pytest-cov; extra == "dev"
Requires-Dist: requests-mock; extra == "dev"
Requires-Dist: twine; extra == "dev"
Requires-Dist: build; extra == "dev"
Requires-Dist: hatch; extra == "dev"
Provides-Extra: doc
Requires-Dist: mkdocs; extra == "doc"
Requires-Dist: mkdocs-material; extra == "doc"
Requires-Dist: mkdocstrings; extra == "doc"
Requires-Dist: mkdocstrings-python; extra == "doc"
Provides-Extra: demo
Requires-Dist: altair<6.0.0,>=5.5.0; extra == "demo"
Requires-Dist: pyaml; extra == "demo"
Requires-Dist: pandas; extra == "demo"
Requires-Dist: tornado; extra == "demo"
Dynamic: license-file
